seiscod/__init__.py
seiscod/errors.py
seiscod/graphic.py
seiscod/picker.py
seiscod/sampling.py
seiscod/stream.py
seiscod/trace.py
seiscod/version.py
seiscod/readwrite/__init__.py
seiscod/readwrite/rawtrace.py
seiscod/readwrite/mseed/__init__.py
seiscod/readwrite/npz/__init__.py
seiscod/readwrite/npz/readnpz.py
seiscod/readwrite/seg2/__init__.py
seiscod/readwrite/seg2/readseg2withobspy.py
seiscod/readwrite/segd/__init__.py
seiscod/readwrite/segd/readsegd1.py
seiscod/readwrite/segy/__init__.py
seiscod/readwrite/segy/createsegyusingobspy.py
seiscod/readwrite/segy/readsegyusingobspy.py
seiscod/readwrite/segy/segyfields.py
seiscod/readwrite/segy/segyheadertocsv.py
seiscod/readwrite/segy/segyview.py
seiscod/readwrite/sig/__init__.py
seiscod/readwrite/sig/readsig.py
seiscod/readwrite/sps/__init__.py
seiscod/readwrite/sps/readsps.py
seiscod/readwrite/tusmus/__init__.py
seiscod/readwrite/tusmus/readtusmus.py
seiscod/readwrite/tusmus/tusmus_to_seispystream.py
seiscod/signal/__init__.py
seiscod/signal/butter.py
seiscod/signal/correlate.py
seiscod/signal/dominantfreq.py
seiscod/signal/fsmooth.py
seiscod/signal/hilbert.py
seiscod/signal/hypermax.py
seiscod/signal/parseval.py
seiscod/signal/pw.py
seiscod/signal/pws.py
seiscod/signal/spectralwhitening.py
seiscod/signal/taper.py
seiscod/signal/waveformclustering.py
seiscod/test/conftest.py
seiscod/test/test_trace.py
seiscod/viz/__init__.py
seiscod/viz/viz.py
seiscod-3.3.9.dist-info/licenses/LICENSE
seiscod-3.3.9.dist-info/METADATA
seiscod-3.3.9.dist-info/WHEEL
seiscod-3.3.9.dist-info/entry_points.txt
seiscod-3.3.9.dist-info/top_level.txt
seiscod-3.3.9.dist-info/RECORD
