Metadata-Version: 2.4
Name: seiscod
Version: 3.3.9
Classifier: Programming Language :: Python :: 3
Classifier: Operating System :: POSIX :: Linux
Classifier: Operating System :: Microsoft :: Windows
Requires-Python: >=3.7
License-File: LICENSE
Requires-Dist: numpy
Requires-Dist: scipy
Requires-Dist: matplotlib
Requires-Dist: ipython
Requires-Dist: pytest
Requires-Dist: numexpr
Requires-Dist: tempoo>=1.0.0
Requires-Dist: pyseg2>=1.3
Requires-Dist: pysegd>=3.0.2
Requires-Dist: pysegd3
Dynamic: license-file
